hdrezkapi/__init__.py
hdrezkapi/common.py
hdrezkapi/hdrezka.py
hdrezkapi/types.py
hdrezkapi-0.0.3.dist-info/LICENSE
hdrezkapi-0.0.3.dist-info/METADATA
hdrezkapi-0.0.3.dist-info/WHEEL
hdrezkapi-0.0.3.dist-info/top_level.txt
hdrezkapi-0.0.3.dist-info/RECORD
