Metadata-Version: 2.1
Name: hdrezkapi
Version: 0.0.3
Summary: a fun little project I did out of boredom
Author-email: miromiro11 <thedrun2004@gmail.com>
Project-URL: Homepage, https://github.com/miromiro11/hdrezka-api
Project-URL: Issues, https://github.com/miromiro11/hdrezka-api/issues
Classifier: Programming Language :: Python :: 3
Classifier: License :: OSI Approved :: MIT License
Classifier: Operating System :: OS Independent
Requires-Python: >=3.8
License-File: LICENSE
Requires-Dist: httpx
Requires-Dist: beautifulsoup4
